usain/__init__.py
usain/usain.py
usain-0.3.1.dist-info/LICENSE
usain-0.3.1.dist-info/METADATA
usain-0.3.1.dist-info/WHEEL
usain-0.3.1.dist-info/top_level.txt
usain-0.3.1.dist-info/RECORD
