Metadata-Version: 2.1
Name: usain
Version: 0.3.1
Summary: Usain is fast lightweight task runner framework
Home-page: https://github.com/adhaamehab/usain
Author: Adham Ehab
Author-email: adhaamehab7@gmail.com
License: MIT license
Keywords: usain
Platform: UNKNOWN
Classifier: Development Status :: 2 - Pre-Alpha
Classifier: Intended Audience :: Developers
Classifier: License :: OSI Approved :: MIT License
Classifier: Natural Language :: English
Classifier: Programming Language :: Python :: 3.5
Classifier: Programming Language :: Python :: 3.6
Classifier: Programming Language :: Python :: 3.7
Requires-Dist: loguru
